app/__init__.py
app/iris_classifier_app.py
knn/__init__.py
knn/cross_validator.py
knn/data_loader.py
knn/iris_model.py
knn/k_nearest_neighbors.py
knn/preprocessor.py
IrisKNNClassifier-1.0.0.dist-info/LICENSE
IrisKNNClassifier-1.0.0.dist-info/METADATA
IrisKNNClassifier-1.0.0.dist-info/WHEEL
IrisKNNClassifier-1.0.0.dist-info/entry_points.txt
IrisKNNClassifier-1.0.0.dist-info/top_level.txt
IrisKNNClassifier-1.0.0.dist-info/RECORD
